rust_timeseries-0.1.7.dist-info/METADATA
rust_timeseries-0.1.7.dist-info/WHEEL
rust_timeseries-0.1.7.dist-info/licenses/LICENSE
rust_timeseries/__init__.py
rust_timeseries/__init__.pyi
rust_timeseries/__pycache__/__init__.cpython-313.pyc
rust_timeseries/_rust_timeseries.cp312-win_amd64.pyd
rust_timeseries/py.typed
rust_timeseries/statistical_tests.pyi
rust_timeseries-0.1.7.dist-info/RECORD
